rctx/__init__.py
rctx/__main__.py
rctx/cli.py
rctx/default_presets.yaml
rctx/tree.py
rctx/utils.py
rctx-0.9.0.dist-info/licenses/LICENSE
tests/__init__.py
tests/test_rctx.py
rctx-0.9.0.dist-info/METADATA
rctx-0.9.0.dist-info/WHEEL
rctx-0.9.0.dist-info/entry_points.txt
rctx-0.9.0.dist-info/top_level.txt
rctx-0.9.0.dist-info/RECORD
